Workbook

Sheet Inputs
B2: PRICES | G2: Diagram of the market
B3: Variable Name | C3: Variable | D3: Description | E3: Value | G3: U: Upstream supplier
B4: Downstream Price | C4: PD | D4: Output prices charged by Firm D (the downstream merging firm). | E4: 20 | G4: D: Downstream producer
B5: Downstream Price | C5: PR | D5: Output prices charged by Firm R (the downstream rival). | E5: =E4 -> 20 | G5: R: Downstream rival
B6: Upstream Price | C6: WD | D6: Input prices charged by Firm U (the upstream merging firm) to Firm D (the downstream merging firm). | E6: =E4*0.5 -> 10 | G6: U and D merge.
B7: Upstream Price | C7: WR | D7: Input prices charged by Firm U (the upstream merging firm) to Firm R (the downstream rival). | E7: =E5*0.5 -> 10 | G7: U
B8: Upstream Average Price | C8: WU | D8: Average input price charged by Firm U (the upstream merging firm) to all downstream (rival) firms, excluding Firm D (the downstream merging firm). | E8: =E4*0.5 -> 10
B10: MARGINS | G10: D | I10: R
B11: Variable Name | C11: Variable | D11: Description | E11: Value
B12: Downstream Margin | C12: MD | D12: Firm D’s (the downstream merging firm) variable profit margin (i.e., its price less its variable cost, PD − CD) expressed as a percentage of its price. That is, MD = (PD − CD) / PD. | E12: 0.5
B13: Downstream Margin | C13: MR | D13: Firm R’s (the downstream rival) variable profit margin (i.e., its price less its variable cost, PR − CR) expressed as a percentage of its price. That is, MR = (PR − CR) / PR. | E13: 0.5
B14: Average Upstream Margin | C14: MU | D14: Firm U’s (the upstream merging firm) average variable profit margin (i.e., its average price charged to all firms except Firm D (the downstream merging firm) less its variable cost, WU − CU) expressed as a percentage of its average price. That is, MU = (WU − CU) / WU. | E14: 0.5
B15: Upstream Margin | C15: MUD | D15: Firm U’s (the upstream merging firm) variable profit margin on input sales to Firm D (the downstream merging firm). | E15: 0.5
B17: DIVERSION RATIOS
B18: Variable Name | C18: Variable | D18: Description | E18: Value | F18: Motivation
B19: Diversion Ratio | C19: DRRD | D19: The fraction of Firm R’s (the downstream rival) sales lost (when Firm R (the downstream rival) raises its price) that are gained by Firm D (the downstream merging firm). | E19: 0.4 | F19: C raises price. Customers purchase less from C and more from B.
B20: Diversion Ratio | C20: DRDU | D20: Sales gained by the upstream supplier divided by revenue lost by downstream partner increasing prices. | E20: 0.25 | F20: B raises price. Customers purchase less from B and more from C. C has to buy more input from A, giving A more revenue.
B21: Diversion Ratio | C21: DRUD | D21: The fraction of Firm U’s (the upstream merging firm) sales lost (when Firm U (the upstream merging firm) raises its price) that are gained by Firm D (the downstream merging firm). | E21: 0.4 | F21: A raises the price it charges to C. C loses sales to end customers (by charging higher prices or producing less), but B gets some of those sales.
B23: PASS-THROUGH RATES
B24: Variable Name | C24: Variable | D24: Description | E24: Value
B25: Upstream Pass-Through Rate | C25: PTRU | D25: The absolute (i.e., dollar) increase in the input price charged to Firm R (the downstream rival) (ΔWR) following an absolute increase in Firm U’s (the upstream merging firm) marginal cost of serving Firm R (the downstream rival) (ΔCU), expressed as a percentage of the increase in marginal cost. That is, PTRU = ΔWR / ΔCU. | E25: 0.5
B26: Downstream Pass-Through Rate | C26: PTRR | D26: The absolute (i.e., dollar) increase in the output price charged by Firm R (the downstream rival) (ΔPR) following an absolute increase in Firm R’s (the downstream rival) marginal cost of production (ΔCR), expressed as a percentage of the increase in marginal cost. That is, PTRR = ΔPR / ΔCR. | E26: 0.5
B28: PURCHASE SHARES
B29: Variable Name | C29: Variable | D29: Description | E29: Value
B30: Purchase Share | C30: SUR | D30: Firm U’s (the upstream merging firm) share of Firm R’s (the downstream rival) total purchases of the relevant input.
B31: Purchase Share Ratio | C31: SURpost / SUR | D31: The ratio of Firm U’s (the upstream merging firm) share of Firm R’s (the downstream rival) input purchases after the target price increase to the share before the input price increase.
B33: ELASTICITIES
B34: Variable Name | C34: Variable | D34: Description | E34: Value
B35: Downstream Pass-Through Elasticity | C35: EP | D35: The percentage increase in Firm R’s (the downstream rival) output price caused by a one-percent increase in Firm U’s (the upstream merging firm) input price charged to Firm R (the downstream rival). That is, EP = (ΔPR / PR) / (ΔWR / WR). Equivalently, EP = PTRR × (ΔCR / ΔWR) × WR / PR. | E35: 0.25
B36: Market Elasticity | C36: E | D36: The percentage reduction in downstream market demand caused by a one-percent increase in the downstream market price. | E36: 1
B37: Purchase Share Elasticity | C37: ESR | D37: The elasticity of the purchase share SUR with respect to an increase in the input price WR that Firm U (the upstream merging firm) charges to Firm R (the downstream rival). | E37: 2.5
B38: Purchase Share Elasticity | C38: ESD | D38: The elasticity of Firm U’s (the upstream merging firm) share of the input purchases of Firm D (the downstream merging firm) with respect to an increase in the input price WD that Firm U (the upstream merging firm) charges to Firm D (the downstream merging firm). | E38: 2.5

Sheet Elasticity_Estimates
B2: SCENARIO 1:
B3: ASSUMING DOWNSTREAM FIRMS ARE SYMMETRIC AND PROFIT-MAXIMIZATION BY THE UPSTREAM MERGING FIRM
B4: EP | C4: PTRR × WR / PR | D4: % change in price of downstream rival divided by % change in price of upstream supplier. | E4: When input prices increase, how much do rivals pass through in their product? | F4: =Inputs!E26 * Inputs!E7 / Inputs!E5 -> 0.25
B5: ESR = ESD | C5: 1 / MU − E × EP | D5: % change in upstream supplier's share of rival's input purchases divided by % change in price of upstream supplier. | E5: When input prices increase, how much do rivals shift their purchases to other suppliers? | F5: =1 / Inputs!E14 - Inputs!E36 * Inputs!E35 -> 1.75

Sheet Upstream_Incentives
B2: SCENARIO 1:
B3: NO INPUT SUBSTITUTION
B4: vGUPPIu | C4: DRUD × MD × PD / WR | D4: =Inputs!E21 * Inputs!E12 * Inputs!E4 / Inputs!E7 -> 0.4 | E4: =D4 -> 0.4
B5: vGUPPIr | C5: vGUPPIu × PTRU × WR / PR | D5: =D4 * Inputs!E25 * Inputs!E7 / Inputs!E5 -> 0.1 | E5: =D5 -> 0.1
B7: SCENARIO 2:
B8: ACCOUNTING FOR INPUT SUBSTITUTION
B9: vGUPPIu | C9: (DRRD × MD × PD / WR) / (1 + MR × ESR / EP) | D9: =(Inputs!E19 * Inputs!E12 * Inputs!E4 / Inputs!E7) / (1 + Inputs!E13 * Inputs!E37 / Inputs!E35) -> 0.066666667 | E9: =D9 -> 0.066666667
B10: SURpost / SUR | C10: 1 − vGUPPIu × PTRU × ESR | D10: =1 - (D9 * Inputs!E25 * Inputs!E37) -> 0.91666667 | E10: =D10 -> 0.91666667
B11: vGUPPIr | C11: vGUPPIu × PTRU × (WR / PR) × (SURpost / SUR) | D11: =D9 * Inputs!E25 * (Inputs!E7 / Inputs!E5) * D10 -> 0.015277778 | E11: =D11 -> 0.015277778

Sheet Downstream_Incentives
B2: SCENARIO 1:
B3: NO ELIMINATION OF DOUBLE MARGINALIZATION (EDM)
B4: vGUPPId1 | C4: DRDU × MU × WU / PD | D4: =Inputs!E20 * Inputs!E14 * Inputs!E8 / Inputs!E4 -> 0.0625 | E4: =D4 -> 0.0625
B6: SCENARIO 2:
B7: ACCOUNTING FOR EDM
B8: vGUPPId2 | C8: vGUPPId1 − MUD × WD / PD | D8: =D4 - Inputs!E15 * Inputs!E6 / Inputs!E4 -> -0.1875 | E8: =D8 -> -0.1875
B10: SCENARIO 3:
B11: ACCOUNTING FOR EDM AND INPUT SUBSTITUTION
B12: vGUPPId3 | C12: vGUPPId2 − ESD × (MUD)2 × WD / PD | D12: =D8 - Inputs!E38 * (Inputs!E15)^2 * Inputs!E6 / Inputs!E4 -> -0.5 | E12: =D12 -> -0.5
